{
    "Classification": "Timepieces, Clocks & Watches",
    "Collection": null,
    "Creators": [
        {
            "ConcatDisplayName": "Pierre le Roi",
            "CreatorID": 2303,
            "Gender": null,
            "Role": "Artist"
        }
    ],
    "CreditLine": "Acquired before 1931",
    "Culture": null,
    "DateBeginYear": 1750,
    "DateEndYear": 1800,
    "DateText": "ca. 1775",
    "Description": "This watch is in a circular gold case, engraved on the back, and decorated with a relief of a bagpiper and children. The background to the scene is enameled in green and yellow, the figures appear to be in silver. The movement is French. The dial is a later replacement.",
    "Dimensions": "Diam: 1 1/4 in. (3.2 cm)",
    "Dynasty": null,
    "Exhibitions": null,
    "Geographies": [
        {
            "GeoHierarchy": "The Thesaurus of Geographic Names\\World\\continents\\Europe\\nations\\",
            "GeoType": "Place of Origin",
            "GeographyID": 1423664,
            "GeographyTerm": "France",
            "Latitude": "46 00",
            "LatitudeDirection": "N",
            "LatitudeNumber": 46.0,
            "Longitude": "002 00",
            "LongitudeDirection": "E",
            "LongitudeNumber": 2.0
        }
    ],
    "Images": [
        {
            "ID": 47042,
            "ImageURLs": {
                "Large": "http://static.thewalters.org/images/PL2_58.78_Fnt_NG_1100.jpg?width=250",
                "Medium": "http://static.thewalters.org/images/PL2_58.78_Fnt_NG_1100.jpg?width=150",
                "Raw": "http://static.thewalters.org/images/PL2_58.78_Fnt_NG_1100.jpg",
                "Small": "http://static.thewalters.org/images/PL2_58.78_Fnt_NG_1100.jpg?width=100",
                "Tiny": "http://static.thewalters.org/images/PL2_58.78_Fnt_NG_1100.jpg?width=50"
            },
            "IsPrimary": true,
            "Rank": 1
        }
    ],
    "Inscriptions": "[Inscription] On backplate: Pre. LeRoy a Paris",
    "Keywords": null,
    "Medium": "gold, silver, enamel",
    "MuseumLocation": {
        "DisplayCurrentLocation": "Not On View",
        "LocationID": 820,
        "LocationString": null
    },
    "ObjectID": 25774,
    "ObjectName": "watches",
    "ObjectNumber": "58.78",
    "OnView": 0,
    "Period": null,
    "Provenance": "Henry Walters, Baltimore [date and mode of acquisition unknown]; Walters Art Museum, 1931, by bequest.",
    "PublicAccessDate": "2013-04-03T14:52:08.627",
    "Reign": null,
    "RelatedObjects": null,
    "ResourceURL": "http://art.thewalters.org/detail/25774",
    "SortNumber": "    58    78                                            ",
    "Style": null,
    "Title": "Gold watch with a relief of a bagpiper and children"
}