{
    "Classification": "Miniatures",
    "Collection": null,
    "Creators": [
        {
            "ConcatDisplayName": "French",
            "CreatorID": 6229,
            "Gender": null,
            "Role": "Artist"
        }
    ],
    "CreditLine": "Acquired Henry Walters, before 1931",
    "Culture": null,
    "DateBeginYear": 1700,
    "DateEndYear": 1799,
    "DateText": "18th century",
    "Description": "At the time of acquisition this miniature was believed to depict Prince Eugene of Savoy after a painting by Hyacinthe Rigaud, but this is unlikely.",
    "Dimensions": "H: 3 3/8 \u00d7 W: 2 11/16 in. (8.5 \u00d7 6.8 cm)",
    "Dynasty": null,
    "Exhibitions": null,
    "Geographies": [
        {
            "GeoHierarchy": "The Thesaurus of Geographic Names\\World\\continents\\Europe\\nations\\",
            "GeoType": "Place of Origin",
            "GeographyID": 1423664,
            "GeographyTerm": "France",
            "Latitude": "46 00",
            "LatitudeDirection": "N",
            "LatitudeNumber": 46.0,
            "Longitude": "002 00",
            "LongitudeDirection": "E",
            "LongitudeNumber": 2.0
        }
    ],
    "Images": [
        {
            "ID": 46327,
            "ImageURLs": {
                "Large": "http://static.thewalters.org/images/PL2_38.35_Fnt_BW.jpg?width=250",
                "Medium": "http://static.thewalters.org/images/PL2_38.35_Fnt_BW.jpg?width=150",
                "Raw": "http://static.thewalters.org/images/PL2_38.35_Fnt_BW.jpg",
                "Small": "http://static.thewalters.org/images/PL2_38.35_Fnt_BW.jpg?width=100",
                "Tiny": "http://static.thewalters.org/images/PL2_38.35_Fnt_BW.jpg?width=50"
            },
            "IsPrimary": true,
            "Rank": 1
        }
    ],
    "Inscriptions": "[Label] On reverse : MACKAY & CHISHOLM / GOLDSMITHS / 57 Princes Street, / EDINBURGH; [Inscription] On reverse, in graphite: Prince Eug\u00e8ne / by Rigaud / Coll / Duc de Berry; [Label] On reverse in ink: 3651 s / 350",
    "Keywords": null,
    "Medium": "watercolor on ivory",
    "MuseumLocation": {
        "DisplayCurrentLocation": "Not On View",
        "LocationID": 2388,
        "LocationString": null
    },
    "ObjectID": 18279,
    "ObjectName": "miniatures (paintings); portraits",
    "ObjectNumber": "38.35",
    "OnView": 0,
    "Period": null,
    "Provenance": "Collection of the Duc and Duchesse de Berry (?); Mackay and Chrisholm, Edinburgh, [date and mode of acquisition unknown]; Henry Walters, Baltimore, [date of acquisition unknown], by purchase; Walters Art Museum, 1931, by bequest.",
    "PublicAccessDate": "2013-04-03T14:52:08.627",
    "Reign": null,
    "RelatedObjects": null,
    "ResourceURL": "http://art.thewalters.org/detail/18279",
    "SortNumber": "    38    35                                            ",
    "Style": null,
    "Title": "Prince Eugene of Savoy (1663-1736) (?)"
}