{
    "Classification": "Wood",
    "Collection": null,
    "Creators": [
        {
            "ConcatDisplayName": "Russian",
            "CreatorID": 6214,
            "Gender": null,
            "Role": "Artist"
        }
    ],
    "CreditLine": "Acquired by Henry Walters",
    "Culture": "Russian",
    "DateBeginYear": 1501,
    "DateEndYear": 1600,
    "DateText": "16th century",
    "Description": "This woodcarved relief icon shows the Crucifixion in front of an architectural rendering of the city of Jerusalem. The apostles Peter and Paul appear at the ends of the arms, preceded by the Virgin, Lazarus' sister Martha, Saint John, and the centurion Longinus. Two Russian monastic saints, Sergius of Radonezh and Cyril of Belozersk, are shown in prayer at the base of the cross. The Three Angels visiting Abraham, at the top, symbolize the Holy Trinity and correspond symbolically with the three holy bishops Gregory, John Chrysostom, and Basil at the bottom. The silver frame was added long after the crucifix had been carved: it has an assayer's mark from the city of Astrakhan dated 1850.",
    "Dimensions": "H: 10 5/8 x W: 6 5/16 x D: 7/8 in. (27 x 16 x 2.2 cm)",
    "Dynasty": null,
    "Exhibitions": [
        {
            "ExhTitle": "A Millennium of Christianity: Russian Art from The Walters Art Gallery",
            "ExhibBeginDate": "1988-12-15",
            "ExhibBeginYear": 1988,
            "ExhibDisplayDate": "December 15, 1988-January 29, 1989",
            "ExhibEndDate": "1989-01-29",
            "ExhibEndYear": 1989,
            "ExhibitionID": 563,
            "LocationID": null,
            "NonWAMExhibition": false,
            "Textblock": "A Millennium of Christianity: Russian Art from The Walters Art Gallery. The Walters Art Gallery, Baltimore. 1988-1989."
        }
    ],
    "Geographies": [
        {
            "GeoHierarchy": "The Thesaurus of Geographic Names\\World\\continents\\Asia\\nations\\Rossiya\\republics\\Rossiya\\oblasts\\Astrakhan'\\inhabited places\\",
            "GeoType": "Place of Origin",
            "GeographyID": 1514940,
            "GeographyTerm": "Astrakhan",
            "Latitude": "46 22",
            "LatitudeDirection": "N",
            "LatitudeNumber": 46.366,
            "Longitude": "048 04",
            "LongitudeDirection": "E",
            "LongitudeNumber": 48.66
        },
        {
            "GeoHierarchy": "The Thesaurus of Geographic Names\\World\\continents\\Asia\\nations\\",
            "GeoType": "Place of Origin",
            "GeographyID": 1509110,
            "GeographyTerm": "Rossiya",
            "Latitude": "60 00",
            "LatitudeDirection": "N",
            "LatitudeNumber": 60.0,
            "Longitude": "047 00",
            "LongitudeDirection": "E",
            "LongitudeNumber": 47.0
        },
        {
            "GeoHierarchy": "The Thesaurus of Geographic Names\\World\\continents\\Asia\\nations\\Yisra'el\\districts (national)\\Yerushalayim, Mehoz\\inhabited places\\",
            "GeoType": "Place Depicted",
            "GeographyID": 1489737,
            "GeographyTerm": "Yerushalayim",
            "Latitude": "31 46",
            "LatitudeDirection": "N",
            "LatitudeNumber": 31.766,
            "Longitude": "035 14",
            "LongitudeDirection": "E",
            "LongitudeNumber": 35.233
        }
    ],
    "Images": [
        {
            "ID": 11289,
            "ImageURLs": {
                "Large": "http://static.thewalters.org/images/PL9_61.295_Fnt_BW.jpg?width=250",
                "Medium": "http://static.thewalters.org/images/PL9_61.295_Fnt_BW.jpg?width=150",
                "Raw": "http://static.thewalters.org/images/PL9_61.295_Fnt_BW.jpg",
                "Small": "http://static.thewalters.org/images/PL9_61.295_Fnt_BW.jpg?width=100",
                "Tiny": "http://static.thewalters.org/images/PL9_61.295_Fnt_BW.jpg?width=50"
            },
            "IsPrimary": true,
            "Rank": 1
        },
        {
            "ID": 12536,
            "ImageURLs": {
                "Large": "http://static.thewalters.org/images/PL7_61.295_Fnt_BW.jpg?width=250",
                "Medium": "http://static.thewalters.org/images/PL7_61.295_Fnt_BW.jpg?width=150",
                "Raw": "http://static.thewalters.org/images/PL7_61.295_Fnt_BW.jpg",
                "Small": "http://static.thewalters.org/images/PL7_61.295_Fnt_BW.jpg?width=100",
                "Tiny": "http://static.thewalters.org/images/PL7_61.295_Fnt_BW.jpg?width=50"
            },
            "IsPrimary": false,
            "Rank": 2
        }
    ],
    "Inscriptions": "[Transcription] On the back of the silver frame: \u041f\u043e\u043c\u0435\u043d\u043e\u0443\u0442\u044a / \u041d\u0438\u043a\u03c9\u043b\u0430\u0467 / \u0415\u043b\u0438\u0437\u0430\u0432\u0435\u0442\u043e\u0443 / \u0441\u03c9 \u0447\u0430\u0434\u044b / \u041c\u0430\u0440\u00ef\u0438 / \u041a\u043b\u0435\u03c9\u043f\u0430\u0442\u0440\u043e\u0443; [Translation] Remember Nicholas [and] Elizabeth with their children Mary [and] Cleopatra.",
    "Keywords": null,
    "Medium": "gilded wood, paint",
    "MuseumLocation": {
        "DisplayCurrentLocation": "Centre Street: Third Floor: Byzantine, Russian, and Ethiopian Icons",
        "LocationID": 3817,
        "LocationString": null
    },
    "ObjectID": 5439,
    "ObjectName": "crucifixes",
    "ObjectNumber": "61.295",
    "OnView": 1,
    "Period": "Early Modern",
    "Provenance": "Henry Walters, Baltimore, [date of acquisition unknown] by purchase; Walters Art Museum, 1931, by bequest.",
    "PublicAccessDate": "2008-09-25T17:15:35.66",
    "Reign": null,
    "RelatedObjects": null,
    "ResourceURL": "http://art.thewalters.org/detail/5439",
    "SortNumber": "    61   295                                            ",
    "Style": null,
    "Title": "Crucifixion with Saints"
}