{
    "Classification": "Ivory & Bone",
    "Collection": null,
    "Creators": [
        {
            "ConcatDisplayName": "Coptic",
            "CreatorID": 6833,
            "Gender": null,
            "Role": "Artist"
        },
        {
            "ConcatDisplayName": "Byzantine",
            "CreatorID": 6640,
            "Gender": null,
            "Role": "Artist"
        }
    ],
    "CreditLine": "Acquired by Henry Walters, 1905",
    "Culture": "Coptic",
    "DateBeginYear": 600,
    "DateEndYear": 800,
    "DateText": "7th-8th century",
    "Description": "This unusually large ivory carving, its shape corresponding to the shape of a tusk, shows the Christ Child embracing his mother in a pose of tender intimacy.  It is one of the earliest examples of what in later Byzantine times was called Eleousa, or \"Virgin of Tenderness.\"  The relief was likely to have been used for private devotion, in either a monastic or domestic setting, as an icon (Greek for \"image\").  Especially striking and typical of the early medieval period in Christian Egypt are the Virgin's large head, fixed gaze, and angular drapery.",
    "Dimensions": "H: 10 1/4 x W: 4 7/8 x D: 1 15/16 in. (26.1 x 12.4 x 5 cm)",
    "Dynasty": null,
    "Exhibitions": [
        {
            "ExhTitle": "Early Christian and Byzantine Art",
            "ExhibBeginDate": "1947-04-24",
            "ExhibBeginYear": 1947,
            "ExhibDisplayDate": "April 24, 1947-June 22, 1947",
            "ExhibEndDate": "1947-06-22",
            "ExhibEndYear": 1947,
            "ExhibitionID": 358,
            "LocationID": null,
            "NonWAMExhibition": false,
            "Textblock": "Early Christian and Byzantine Art. Baltimore Museum of Art, Baltimore. 1947."
        },
        {
            "ExhTitle": "Ivory: The Sumptuous Art",
            "ExhibBeginDate": "1983-10-14",
            "ExhibBeginYear": 1983,
            "ExhibDisplayDate": "October 14, 1983-January 15, 1984",
            "ExhibEndDate": "1984-01-15",
            "ExhibEndYear": 1984,
            "ExhibitionID": 215,
            "LocationID": null,
            "NonWAMExhibition": false,
            "Textblock": "Ivory: The Sumptuous Art. The Walters Art Gallery, Baltimore. 1983-1984."
        },
        {
            "ExhTitle": "D\u00e9j\u00e0 Vu? Recurrence",
            "ExhibBeginDate": "2007-09-19",
            "ExhibBeginYear": 2007,
            "ExhibDisplayDate": "September 19, 2007-January 20, 2008",
            "ExhibEndDate": "2008-01-20",
            "ExhibEndYear": 2008,
            "ExhibitionID": 2816,
            "LocationID": null,
            "NonWAMExhibition": false,
            "Textblock": "D\u00e9j\u00e0 Vu? Recurrence. The Walters Art Museum, Baltimore. 2007-2008."
        }
    ],
    "Geographies": [
        {
            "GeoHierarchy": "The Thesaurus of Geographic Names\\World\\continents\\Africa\\nations\\",
            "GeoType": "Place of Origin",
            "GeographyID": 1543485,
            "GeographyTerm": "Misr",
            "Latitude": "27 00",
            "LatitudeDirection": "N",
            "LatitudeNumber": 27.0,
            "Longitude": "030 00",
            "LongitudeDirection": "E",
            "LongitudeNumber": 30.0
        },
        {
            "GeoHierarchy": "The Thesaurus of Geographic Names\\World\\continents\\Africa\\nations\\",
            "GeoType": "Place of Origin",
            "GeographyID": 1543485,
            "GeographyTerm": "Misr",
            "Latitude": "27 00",
            "LatitudeDirection": "N",
            "LatitudeNumber": 27.0,
            "Longitude": "030 00",
            "LongitudeDirection": "E",
            "LongitudeNumber": 30.0
        }
    ],
    "Images": [
        {
            "ID": 7491,
            "ImageURLs": {
                "Large": "http://static.thewalters.org/images/PL1_71.297_Fnt_TR_C82.jpg?width=250",
                "Medium": "http://static.thewalters.org/images/PL1_71.297_Fnt_TR_C82.jpg?width=150",
                "Raw": "http://static.thewalters.org/images/PL1_71.297_Fnt_TR_C82.jpg",
                "Small": "http://static.thewalters.org/images/PL1_71.297_Fnt_TR_C82.jpg?width=100",
                "Tiny": "http://static.thewalters.org/images/PL1_71.297_Fnt_TR_C82.jpg?width=50"
            },
            "IsPrimary": true,
            "Rank": 1
        },
        {
            "ID": 36038,
            "ImageURLs": {
                "Large": "http://static.thewalters.org/images/PL2_71.297_Fnt_NG_413.jpg?width=250",
                "Medium": "http://static.thewalters.org/images/PL2_71.297_Fnt_NG_413.jpg?width=150",
                "Raw": "http://static.thewalters.org/images/PL2_71.297_Fnt_NG_413.jpg",
                "Small": "http://static.thewalters.org/images/PL2_71.297_Fnt_NG_413.jpg?width=100",
                "Tiny": "http://static.thewalters.org/images/PL2_71.297_Fnt_NG_413.jpg?width=50"
            },
            "IsPrimary": false,
            "Rank": 2
        }
    ],
    "Inscriptions": null,
    "Keywords": "Byzantine art; icon; Virgin; Christ; tusk; devotion; Madonna; Jesus Christ",
    "Medium": "ivory",
    "MuseumLocation": {
        "DisplayCurrentLocation": "Centre Street: Third Floor: Early Byzantine Art",
        "LocationID": 3807,
        "LocationString": null
    },
    "ObjectID": 6580,
    "ObjectName": "relief",
    "ObjectNumber": "71.297",
    "OnView": 1,
    "Period": "Early Medieval",
    "Provenance": "Cologne, 1870s; M.-B. Meyers, Strasbourg, 1877, by purchase; Sale, H\u00f4tel Drouot, Paris, November 26, 1877; Michel Boy, Paris [date of acquisition unknown], by purchase; Sale, H\u00f4tel Drouot, Paris, May 15, 1905, no. 240; Henry Walters, Baltimore, 1905, by purchase; Walters Art Museum, 1931, by bequest.",
    "PublicAccessDate": "2008-09-25T17:15:35.847",
    "Reign": null,
    "RelatedObjects": null,
    "ResourceURL": "http://art.thewalters.org/detail/6580",
    "SortNumber": "    71   297                                            ",
    "Style": null,
    "Title": "Virgin and Child"
}