{
    "Classification": "Gold, Silver & Jewelry",
    "Collection": null,
    "Creators": [
        {
            "ConcatDisplayName": "Russian",
            "CreatorID": 6214,
            "Gender": null,
            "Role": "Artist"
        }
    ],
    "CreditLine": "Acquired by Henry Walters, 1930",
    "Culture": "Russian",
    "DateBeginYear": 1745,
    "DateEndYear": 1745,
    "DateText": "1745",
    "Description": "Around the body of the cup is a silver envelope with pierced designs and three portrait medallions in repouss\u00e9.  The finial of the cover is designed as a double-headed eagle.",
    "Dimensions": "5 13/16 in. (14.7 cm)",
    "Dynasty": "House of Romanov",
    "Exhibitions": [
        {
            "ExhTitle": "Russian Art: Icons and Decorative Arts from the Origin to the Twentieth Century",
            "ExhibBeginDate": "1959-11-09",
            "ExhibBeginYear": 1959,
            "ExhibDisplayDate": "November 9, 1959-January 3, 1960",
            "ExhibEndDate": "1960-01-03",
            "ExhibEndYear": 1960,
            "ExhibitionID": 69,
            "LocationID": null,
            "NonWAMExhibition": false,
            "Textblock": "Russian Art: Icons and Decorative Arts from the Origin to the Twentieth Century. The Walters Art Gallery, Baltimore. 1959-1960."
        }
    ],
    "Geographies": [
        {
            "GeoHierarchy": "The Thesaurus of Geographic Names\\World\\continents\\Asia\\nations\\Rossiya\\republics\\Rossiya\\autonomous cities\\",
            "GeoType": "Place of Origin",
            "GeographyID": 1510723,
            "GeographyTerm": "Moskva",
            "Latitude": "55 45",
            "LatitudeDirection": "N",
            "LatitudeNumber": 55.75,
            "Longitude": "037 42",
            "LongitudeDirection": "E",
            "LongitudeNumber": 37.7
        }
    ],
    "Images": [
        {
            "ID": 25287,
            "ImageURLs": {
                "Large": "http://static.thewalters.org/images/PS1_57.807_VwA_DD_T10.jpg?width=250",
                "Medium": "http://static.thewalters.org/images/PS1_57.807_VwA_DD_T10.jpg?width=150",
                "Raw": "http://static.thewalters.org/images/PS1_57.807_VwA_DD_T10.jpg",
                "Small": "http://static.thewalters.org/images/PS1_57.807_VwA_DD_T10.jpg?width=100",
                "Tiny": "http://static.thewalters.org/images/PS1_57.807_VwA_DD_T10.jpg?width=50"
            },
            "IsPrimary": true,
            "Rank": 1
        },
        {
            "ID": 25288,
            "ImageURLs": {
                "Large": "http://static.thewalters.org/images/PS1_57.807_VwB_DD_T10.jpg?width=250",
                "Medium": "http://static.thewalters.org/images/PS1_57.807_VwB_DD_T10.jpg?width=150",
                "Raw": "http://static.thewalters.org/images/PS1_57.807_VwB_DD_T10.jpg",
                "Small": "http://static.thewalters.org/images/PS1_57.807_VwB_DD_T10.jpg?width=100",
                "Tiny": "http://static.thewalters.org/images/PS1_57.807_VwB_DD_T10.jpg?width=50"
            },
            "IsPrimary": false,
            "Rank": 2
        },
        {
            "ID": 25289,
            "ImageURLs": {
                "Large": "http://static.thewalters.org/images/PS1_57.807_VwC_DD_T10.jpg?width=250",
                "Medium": "http://static.thewalters.org/images/PS1_57.807_VwC_DD_T10.jpg?width=150",
                "Raw": "http://static.thewalters.org/images/PS1_57.807_VwC_DD_T10.jpg",
                "Small": "http://static.thewalters.org/images/PS1_57.807_VwC_DD_T10.jpg?width=100",
                "Tiny": "http://static.thewalters.org/images/PS1_57.807_VwC_DD_T10.jpg?width=50"
            },
            "IsPrimary": false,
            "Rank": 3
        },
        {
            "ID": 25286,
            "ImageURLs": {
                "Large": "http://static.thewalters.org/images/PS1_57.807_MrkA_DD_T10.jpg?width=250",
                "Medium": "http://static.thewalters.org/images/PS1_57.807_MrkA_DD_T10.jpg?width=150",
                "Raw": "http://static.thewalters.org/images/PS1_57.807_MrkA_DD_T10.jpg",
                "Small": "http://static.thewalters.org/images/PS1_57.807_MrkA_DD_T10.jpg?width=100",
                "Tiny": "http://static.thewalters.org/images/PS1_57.807_MrkA_DD_T10.jpg?width=50"
            },
            "IsPrimary": false,
            "Rank": 4
        }
    ],
    "Inscriptions": "Bears the marks of an unknown maker 'VD', who was active 1741-1753. It also bears the assayer's mark of Andrei Zaitsev who was active from 1735-1749. Several marks on rim: Moscow 1745.",
    "Keywords": null,
    "Medium": "silver, parcel gilt",
    "MuseumLocation": {
        "DisplayCurrentLocation": "Not On View",
        "LocationID": 4277,
        "LocationString": null
    },
    "ObjectID": 24053,
    "ObjectName": "cups;drinking vessels",
    "ObjectNumber": "57.807",
    "OnView": 1,
    "Period": "Early Modern",
    "Provenance": "Alexandre Polovtsoff (Aleksandr Aleksandrovich Polovtsov), St. Petersburg and Paris, by purchase; Henry Walters, Baltimore, 1930, by purchase; Walters Art Museum, 1931, by bequest.",
    "PublicAccessDate": "2008-09-25T17:14:37.457",
    "Reign": "Elizabeth I (1741-1762)",
    "RelatedObjects": null,
    "ResourceURL": "http://art.thewalters.org/detail/24053",
    "SortNumber": "    57   807                                            ",
    "Style": "Baroque",
    "Title": "Covered Cup with Large Foot"
}