{
    "Classification": "Manuscripts & Rare Books",
    "Collection": null,
    "Creators": [
        {
            "ConcatDisplayName": "Nur al-Din `Abd al-Rahman ibn Ahmad Jami (Persian, died 898 AH/AD 1492)",
            "CreatorID": 15674,
            "Gender": "male",
            "Role": "Author"
        },
        {
            "ConcatDisplayName": "Muhammad Zaman al-Tabrizi",
            "CreatorID": 18666,
            "Gender": null,
            "Role": "Scribe"
        }
    ],
    "CreditLine": "Acquired by Henry Walters",
    "Culture": "Islamic",
    "DateBeginYear": 1589,
    "DateEndYear": 1590,
    "DateText": "998 AH/AD 1589-1590",
    "Description": "Walters manuscript W.651 is an illuminated and illustrated manuscript of a small collection of short love poems of the type called tarji`band by Nur al-Din \"Abd al-Rahman Jami (died 898 AH/AD 1492). It was copied in black Nasta\"liq script by the calligrapher Muhammad Zaman al-Tabrizi in 998 AH/AD 1589-1590 in Safavid Iran. The text is written on orange-tinted paper, and the bluish-green borders are illuminated throughout. The manuscript opens with an incipit page with illuminated headpiece (fol. 1b), and there are 2 illustrations (fols. 3a and 6a). The Qajar lacquer binding is decorated with floral motifs and is inscribed with verses attributed to Imam \"Ali ibn Abi Talib. An ownership statement is present, written by Husayn Qavam Daftar (?) and dated 1311 AH/AD 1893-1894, stating that this precious book was bought for his son, Mahmud Askani, from a woman for 10 ashrafis (gold dinars) (fol. 6b).",
    "Dimensions": "Folio H: 6 7/8 x W: 4 5/16 in. (17.5 x 11.0 cm)",
    "Dynasty": "Safavid Dynasty, Qajar Dynasty",
    "Exhibitions": null,
    "Geographies": [
        {
            "GeoHierarchy": "The Thesaurus of Geographic Names\\World\\continents\\Asia\\nations\\",
            "GeoType": "Place of Origin",
            "GeographyID": 1507667,
            "GeographyTerm": "\u00ceran",
            "Latitude": "32 00",
            "LatitudeDirection": "N",
            "LatitudeNumber": 32.0,
            "Longitude": "053 00",
            "LongitudeDirection": "E",
            "LongitudeNumber": 53.0
        },
        {
            "GeoHierarchy": "The Thesaurus of Geographic Names\\World\\continents\\Asia\\nations\\",
            "GeoType": "Place of Origin",
            "GeographyID": 1507667,
            "GeographyTerm": "\u00ceran",
            "Latitude": "32 00",
            "LatitudeDirection": "N",
            "LatitudeNumber": 32.0,
            "Longitude": "053 00",
            "LongitudeDirection": "E",
            "LongitudeNumber": 53.0
        }
    ],
    "Images": [
        {
            "ID": 28873,
            "ImageURLs": {
                "Large": "http://static.thewalters.org/images/CPS_W.651.binding_TopExt_DD_UpperBoardOutside.jpg?width=250",
                "Medium": "http://static.thewalters.org/images/CPS_W.651.binding_TopExt_DD_UpperBoardOutside.jpg?width=150",
                "Raw": "http://static.thewalters.org/images/CPS_W.651.binding_TopExt_DD_UpperBoardOutside.jpg",
                "Small": "http://static.thewalters.org/images/CPS_W.651.binding_TopExt_DD_UpperBoardOutside.jpg?width=100",
                "Tiny": "http://static.thewalters.org/images/CPS_W.651.binding_TopExt_DD_UpperBoardOutside.jpg?width=50"
            },
            "IsPrimary": true,
            "Rank": 1
        },
        {
            "ID": 28874,
            "ImageURLs": {
                "Large": "http://static.thewalters.org/images/CPS_W.651.binding_TopInt_DD_UpperBoardInside.jpg?width=250",
                "Medium": "http://static.thewalters.org/images/CPS_W.651.binding_TopInt_DD_UpperBoardInside.jpg?width=150",
                "Raw": "http://static.thewalters.org/images/CPS_W.651.binding_TopInt_DD_UpperBoardInside.jpg",
                "Small": "http://static.thewalters.org/images/CPS_W.651.binding_TopInt_DD_UpperBoardInside.jpg?width=100",
                "Tiny": "http://static.thewalters.org/images/CPS_W.651.binding_TopInt_DD_UpperBoardInside.jpg?width=50"
            },
            "IsPrimary": false,
            "Rank": 2
        },
        {
            "ID": 28872,
            "ImageURLs": {
                "Large": "http://static.thewalters.org/images/CPS_W.651.binding_BotInt_DD_LowerBoardInside.jpg?width=250",
                "Medium": "http://static.thewalters.org/images/CPS_W.651.binding_BotInt_DD_LowerBoardInside.jpg?width=150",
                "Raw": "http://static.thewalters.org/images/CPS_W.651.binding_BotInt_DD_LowerBoardInside.jpg",
                "Small": "http://static.thewalters.org/images/CPS_W.651.binding_BotInt_DD_LowerBoardInside.jpg?width=100",
                "Tiny": "http://static.thewalters.org/images/CPS_W.651.binding_BotInt_DD_LowerBoardInside.jpg?width=50"
            },
            "IsPrimary": false,
            "Rank": 3
        },
        {
            "ID": 33836,
            "ImageURLs": {
                "Large": "http://static.thewalters.org/images/CPS_W.651_TopExt_DD_UBO.jpg?width=250",
                "Medium": "http://static.thewalters.org/images/CPS_W.651_TopExt_DD_UBO.jpg?width=150",
                "Raw": "http://static.thewalters.org/images/CPS_W.651_TopExt_DD_UBO.jpg",
                "Small": "http://static.thewalters.org/images/CPS_W.651_TopExt_DD_UBO.jpg?width=100",
                "Tiny": "http://static.thewalters.org/images/CPS_W.651_TopExt_DD_UBO.jpg?width=50"
            },
            "IsPrimary": false,
            "Rank": 4
        }
    ],
    "Inscriptions": null,
    "Keywords": "Islamic; Persian; Safavid; Qajar; Book; Codex; Colophon; Illumination; Illustration; Manuscript; Iran; Literature -- Poetry",
    "Medium": "ink and pigments on orange-tinted paper with bluish-green borders, covered with lacquer",
    "MuseumLocation": {
        "DisplayCurrentLocation": "Not On View",
        "LocationID": 2347,
        "LocationString": null
    },
    "ObjectID": 38101,
    "ObjectName": "illuminated manuscripts",
    "ObjectNumber": "W.651",
    "OnView": 0,
    "Period": "Safavid, Qajar",
    "Provenance": "Mahmud Askani, 1893-1894, by purchase [ownership statement on fol. 6b written by Husayn Qavam Daftar (?) and dated 1311 AH/AD 1893-1894 stating that this precious book was bought for his son Mahmud Askani from a woman for 10 ashrafis (gold dinars)]; Henry Walters, Baltimore [date and mode of acquisition unknown]; Walters Art Museum, 1931, by bequest.",
    "PublicAccessDate": "2014-01-24T13:51:40.93",
    "Reign": null,
    "RelatedObjects": [
        {
            "ObjectID": 81475,
            "RelationType": "Part of a Book"
        },
        {
            "ObjectID": 81476,
            "RelationType": "Part of a Book"
        },
        {
            "ObjectID": 81477,
            "RelationType": "Part of a Book"
        },
        {
            "ObjectID": 81478,
            "RelationType": "Part of a Book"
        },
        {
            "ObjectID": 81479,
            "RelationType": "Part of a Book"
        },
        {
            "ObjectID": 81480,
            "RelationType": "Part of a Book"
        },
        {
            "ObjectID": 81481,
            "RelationType": "Part of a Book"
        },
        {
            "ObjectID": 81482,
            "RelationType": "Part of a Book"
        },
        {
            "ObjectID": 81483,
            "RelationType": "Part of a Book"
        },
        {
            "ObjectID": 81484,
            "RelationType": "Part of a Book"
        },
        {
            "ObjectID": 81485,
            "RelationType": "Part of a Book"
        },
        {
            "ObjectID": 81488,
            "RelationType": "Part of a Book"
        }
    ],
    "ResourceURL": "http://art.thewalters.org/detail/38101",
    "SortNumber": "W        651                                            ",
    "Style": null,
    "Title": "Poems (tarji'band)"
}