{
    "Classification": "Ceramics",
    "Collection": null,
    "Creators": [
        {
            "ConcatDisplayName": "Venetian ()",
            "CreatorID": 6200,
            "Gender": null,
            "Role": "Ceramicist"
        }
    ],
    "CreditLine": "Acquired by Henry Walters, 1917",
    "Culture": null,
    "DateBeginYear": 1510,
    "DateEndYear": 1515,
    "DateText": "1510-1515",
    "Description": "This bowl is painted in gold lustre and in blue. On the interior around the side is a band of alternating diamonds and ovals; in the center are two banderoles in a square edged by four petals, the whole is set within four concentric circles and surrounded by a wide border of pointed rays alternating with stylized buds. On the exterior is a longitudinal band of buds around the side; painted oblique gadroons on the lower part of the body and a band of radial leaves around the foot.",
    "Dimensions": "H: 6 1/4 x Diam: 10 5/16 in. (15.9 x 26.2 cm)",
    "Dynasty": null,
    "Exhibitions": null,
    "Geographies": [
        {
            "GeoHierarchy": "The Thesaurus of Geographic Names\\World\\continents\\Europe\\nations\\Italia\\regions\\Umbria\\provinces\\Perugia\\inhabited places\\",
            "GeoType": "Place of Origin",
            "GeographyID": 1437433,
            "GeographyTerm": "Deruta",
            "Latitude": "42 59",
            "LatitudeDirection": "N",
            "LatitudeNumber": 42.983,
            "Longitude": "012 25",
            "LongitudeDirection": "E",
            "LongitudeNumber": 12.416
        }
    ],
    "Images": [
        {
            "ID": 46455,
            "ImageURLs": {
                "Large": "http://static.thewalters.org/images/PL2_48.1763_Fnt_BW.jpg?width=250",
                "Medium": "http://static.thewalters.org/images/PL2_48.1763_Fnt_BW.jpg?width=150",
                "Raw": "http://static.thewalters.org/images/PL2_48.1763_Fnt_BW.jpg",
                "Small": "http://static.thewalters.org/images/PL2_48.1763_Fnt_BW.jpg?width=100",
                "Tiny": "http://static.thewalters.org/images/PL2_48.1763_Fnt_BW.jpg?width=50"
            },
            "IsPrimary": true,
            "Rank": 1
        }
    ],
    "Inscriptions": "[Transcription] In the center interior, within an ornamented square, in stylized gothic text: N",
    "Keywords": null,
    "Medium": "earthenware with tin glaze (maiolica) with luster decoration",
    "MuseumLocation": {
        "DisplayCurrentLocation": "Not On View",
        "LocationID": 5359,
        "LocationString": null
    },
    "ObjectID": 36720,
    "ObjectName": "bowls (vessels)",
    "ObjectNumber": "48.1763",
    "OnView": 0,
    "Period": "Renaissance",
    "Provenance": "T. B. Clarke [date and mode of acquisition unknown] [no. 662]; Henry Walters, Baltimore, 1917, by purchase; Walters Art Museum, 1931, by bequest.",
    "PublicAccessDate": "2013-09-15T14:36:37.64",
    "Reign": null,
    "RelatedObjects": null,
    "ResourceURL": "http://art.thewalters.org/detail/36720",
    "SortNumber": "    48  1763                                            ",
    "Style": null,
    "Title": "Large Bowl with Foot and Vertical Side"
}