{
    "Classification": "Timepieces, Clocks & Watches",
    "Collection": null,
    "Creators": [
        {
            "ConcatDisplayName": "Nikolaki (Greek (?))",
            "CreatorID": 15349,
            "Gender": null,
            "Role": "Clockmaker"
        },
        {
            "ConcatDisplayName": "Apprenticed to Swiss",
            "CreatorID": 6290,
            "Gender": null,
            "Role": "Master Craftsman"
        }
    ],
    "CreditLine": "Acquired by Henry Walters",
    "Culture": "Ottoman",
    "DateBeginYear": 1700,
    "DateEndYear": 1799,
    "DateText": "18th century",
    "Description": "The maker of this watch, who signed himself \"Nikolaki,\" was probably of Greek ancestry and had served as an apprentice to a watchmaker from Geneva, Switzerland, who worked in Constantinople (present-day Istanbul).  Due to the great demand for watches in Turkey, several watchmakers from Geneva made their homes in Constantinople and trained local craftsmen in their art.  The Turkish taste was for colorful and visually complicated watches.  The raised pearls on the dial permit the time to be \"told\" in the dark or by the blind. Even the movement inside is decorated with pearls, although some are now missing.",
    "Dimensions": "H: 2 3/16 \u00d7 W: 1 5/8 \u00d7 D: 1 in. (5.5 \u00d7 4.2 \u00d7 2.5 cm)\r\nH with loop: 2 1/2 in. (6.3 cm)",
    "Dynasty": "Ottoman Dynasty",
    "Exhibitions": null,
    "Geographies": [
        {
            "GeoHierarchy": "The Thesaurus of Geographic Names\\World\\continents\\Asia\\nations\\T\u00fcrkiye\\regions\\Marmara\\provinces\\Istanbul\\inhabited places\\",
            "GeoType": "Place of Origin",
            "GeographyID": 1501274,
            "GeographyTerm": "Istanbul",
            "Latitude": "41 02",
            "LatitudeDirection": "N",
            "LatitudeNumber": 41.33,
            "Longitude": "028 57",
            "LongitudeDirection": "E",
            "LongitudeNumber": 28.95
        },
        {
            "GeoHierarchy": "The Thesaurus of Geographic Names\\World\\continents\\Asia\\nations\\T\u00fcrkiye\\regions\\Marmara\\provinces\\Istanbul\\inhabited places\\",
            "GeoType": "Place of Origin",
            "GeographyID": 1501274,
            "GeographyTerm": "Istanbul",
            "Latitude": "41 02",
            "LatitudeDirection": "N",
            "LatitudeNumber": 41.33,
            "Longitude": "028 57",
            "LongitudeDirection": "E",
            "LongitudeNumber": 28.95
        }
    ],
    "Images": [
        {
            "ID": 49913,
            "ImageURLs": {
                "Large": "http://static.thewalters.org/images/PS1_58.81_FntClosd_DD_T13.jpg?width=250",
                "Medium": "http://static.thewalters.org/images/PS1_58.81_FntClosd_DD_T13.jpg?width=150",
                "Raw": "http://static.thewalters.org/images/PS1_58.81_FntClosd_DD_T13.jpg",
                "Small": "http://static.thewalters.org/images/PS1_58.81_FntClosd_DD_T13.jpg?width=100",
                "Tiny": "http://static.thewalters.org/images/PS1_58.81_FntClosd_DD_T13.jpg?width=50"
            },
            "IsPrimary": true,
            "Rank": 1
        },
        {
            "ID": 49914,
            "ImageURLs": {
                "Large": "http://static.thewalters.org/images/PS1_58.81_FntOpn_DD_T13.jpg?width=250",
                "Medium": "http://static.thewalters.org/images/PS1_58.81_FntOpn_DD_T13.jpg?width=150",
                "Raw": "http://static.thewalters.org/images/PS1_58.81_FntOpn_DD_T13.jpg",
                "Small": "http://static.thewalters.org/images/PS1_58.81_FntOpn_DD_T13.jpg?width=100",
                "Tiny": "http://static.thewalters.org/images/PS1_58.81_FntOpn_DD_T13.jpg?width=50"
            },
            "IsPrimary": false,
            "Rank": 2
        },
        {
            "ID": 49915,
            "ImageURLs": {
                "Large": "http://static.thewalters.org/images/PS1_58.81_Opn_DD_T13.jpg?width=250",
                "Medium": "http://static.thewalters.org/images/PS1_58.81_Opn_DD_T13.jpg?width=150",
                "Raw": "http://static.thewalters.org/images/PS1_58.81_Opn_DD_T13.jpg",
                "Small": "http://static.thewalters.org/images/PS1_58.81_Opn_DD_T13.jpg?width=100",
                "Tiny": "http://static.thewalters.org/images/PS1_58.81_Opn_DD_T13.jpg?width=50"
            },
            "IsPrimary": false,
            "Rank": 3
        },
        {
            "ID": 49916,
            "ImageURLs": {
                "Large": "http://static.thewalters.org/images/PS1_58.81_OpnFntSide_DD_T13.jpg?width=250",
                "Medium": "http://static.thewalters.org/images/PS1_58.81_OpnFntSide_DD_T13.jpg?width=150",
                "Raw": "http://static.thewalters.org/images/PS1_58.81_OpnFntSide_DD_T13.jpg",
                "Small": "http://static.thewalters.org/images/PS1_58.81_OpnFntSide_DD_T13.jpg?width=100",
                "Tiny": "http://static.thewalters.org/images/PS1_58.81_OpnFntSide_DD_T13.jpg?width=50"
            },
            "IsPrimary": false,
            "Rank": 4
        },
        {
            "ID": 49917,
            "ImageURLs": {
                "Large": "http://static.thewalters.org/images/PS1_58.81_OpnLftSide_DD_T13.jpg?width=250",
                "Medium": "http://static.thewalters.org/images/PS1_58.81_OpnLftSide_DD_T13.jpg?width=150",
                "Raw": "http://static.thewalters.org/images/PS1_58.81_OpnLftSide_DD_T13.jpg",
                "Small": "http://static.thewalters.org/images/PS1_58.81_OpnLftSide_DD_T13.jpg?width=100",
                "Tiny": "http://static.thewalters.org/images/PS1_58.81_OpnLftSide_DD_T13.jpg?width=50"
            },
            "IsPrimary": false,
            "Rank": 5
        },
        {
            "ID": 49918,
            "ImageURLs": {
                "Large": "http://static.thewalters.org/images/PS1_58.81_OpnRtSide_DD_T13.jpg?width=250",
                "Medium": "http://static.thewalters.org/images/PS1_58.81_OpnRtSide_DD_T13.jpg?width=150",
                "Raw": "http://static.thewalters.org/images/PS1_58.81_OpnRtSide_DD_T13.jpg",
                "Small": "http://static.thewalters.org/images/PS1_58.81_OpnRtSide_DD_T13.jpg?width=100",
                "Tiny": "http://static.thewalters.org/images/PS1_58.81_OpnRtSide_DD_T13.jpg?width=50"
            },
            "IsPrimary": false,
            "Rank": 6
        },
        {
            "ID": 49919,
            "ImageURLs": {
                "Large": "http://static.thewalters.org/images/PS1_58.81_TopInt_DD_T13.jpg?width=250",
                "Medium": "http://static.thewalters.org/images/PS1_58.81_TopInt_DD_T13.jpg?width=150",
                "Raw": "http://static.thewalters.org/images/PS1_58.81_TopInt_DD_T13.jpg",
                "Small": "http://static.thewalters.org/images/PS1_58.81_TopInt_DD_T13.jpg?width=100",
                "Tiny": "http://static.thewalters.org/images/PS1_58.81_TopInt_DD_T13.jpg?width=50"
            },
            "IsPrimary": false,
            "Rank": 7
        },
        {
            "ID": 49911,
            "ImageURLs": {
                "Large": "http://static.thewalters.org/images/PS1_58.81_BackClosd_DD_T13.jpg?width=250",
                "Medium": "http://static.thewalters.org/images/PS1_58.81_BackClosd_DD_T13.jpg?width=150",
                "Raw": "http://static.thewalters.org/images/PS1_58.81_BackClosd_DD_T13.jpg",
                "Small": "http://static.thewalters.org/images/PS1_58.81_BackClosd_DD_T13.jpg?width=100",
                "Tiny": "http://static.thewalters.org/images/PS1_58.81_BackClosd_DD_T13.jpg?width=50"
            },
            "IsPrimary": false,
            "Rank": 8
        },
        {
            "ID": 49912,
            "ImageURLs": {
                "Large": "http://static.thewalters.org/images/PS1_58.81_BackOpn_DD_T13.jpg?width=250",
                "Medium": "http://static.thewalters.org/images/PS1_58.81_BackOpn_DD_T13.jpg?width=150",
                "Raw": "http://static.thewalters.org/images/PS1_58.81_BackOpn_DD_T13.jpg",
                "Small": "http://static.thewalters.org/images/PS1_58.81_BackOpn_DD_T13.jpg?width=100",
                "Tiny": "http://static.thewalters.org/images/PS1_58.81_BackOpn_DD_T13.jpg?width=50"
            },
            "IsPrimary": false,
            "Rank": 9
        }
    ],
    "Inscriptions": "[Translation] Nikolaki",
    "Keywords": null,
    "Medium": "niello, resin and gilt on silver case; \"basse-taille\" enamel on gilt silver and pearl dial, gilt on brass, steel, and pearl movement",
    "MuseumLocation": {
        "DisplayCurrentLocation": "Not on View",
        "LocationID": 4056,
        "LocationString": null
    },
    "ObjectID": 29083,
    "ObjectName": "watches",
    "ObjectNumber": "58.81",
    "OnView": 0,
    "Period": "Early Modern",
    "Provenance": "Henry Walters, Baltimore [date and mode of acquisition unknown]; Walters Art Museum, 1931, by bequest.",
    "PublicAccessDate": "2013-06-10T13:27:45.513",
    "Reign": null,
    "RelatedObjects": null,
    "ResourceURL": "http://art.thewalters.org/detail/29083",
    "SortNumber": "    58    81                                            ",
    "Style": null,
    "Title": "Watch for the Turkish Market"
}