{
    "Classification": "Metal",
    "Collection": null,
    "Creators": [
        {
            "ConcatDisplayName": "Nepalese",
            "CreatorID": 15526,
            "Gender": null,
            "Role": "Artist"
        }
    ],
    "CreditLine": "Gift of John and Berthe Ford, 2002",
    "Culture": null,
    "DateBeginYear": 1288,
    "DateEndYear": 1312,
    "DateText": "ca. 1300",
    "Description": "As a compassionate bodhisattva who helps those in need and removes obstacles to enlightenment, Tara is regarded as a female counterpart to Avalokiteshvara. Like him, the lotus is her attribute, and both are believed to be saviors to their devotees. Some Buddhists also consider Tara to be a supreme goddess, the mother of all buddhas. Here, she makes the gesture of teaching with her left hand while holding her right hand in generous bestowal.",
    "Dimensions": "H: 5 1/2 \u00d7 W: 4 1/8 \u00d7 D: 4 in. (13.97 \u00d7 10.48 \u00d7 10.16 cm)",
    "Dynasty": null,
    "Exhibitions": [
        {
            "ExhTitle": "Cupola and Bridge Reinstallation 2014",
            "ExhibBeginDate": "2014-11-29",
            "ExhibBeginYear": 2014,
            "ExhibDisplayDate": "November 26, 2014 - November 26, 2017",
            "ExhibEndDate": "2017-11-26",
            "ExhibEndYear": 2017,
            "ExhibitionID": 3361,
            "LocationID": 5008,
            "NonWAMExhibition": false,
            "Textblock": "Cupola and Bridge Reinstallation 2014. 2014-2017."
        },
        {
            "ExhTitle": "Desire and Devotion: Art from India, Nepal, and Tibet in the John and Berthe Ford Collection",
            "ExhibBeginDate": "2001-10-20",
            "ExhibBeginYear": 2001,
            "ExhibDisplayDate": "October 20, 2001-May 25, 2003",
            "ExhibEndDate": "2003-05-25",
            "ExhibEndYear": 2003,
            "ExhibitionID": 2071,
            "LocationID": null,
            "NonWAMExhibition": false,
            "Textblock": "Desire and Devotion: Art from India, Nepal, and Tibet in the John and Berthe Ford Collection. The Walters Art Museum, Baltimore; Santa Barbara Museum of Art, Santa Barbara; Albuquerque Museum, Albuquerque; Birmingham Museum of Art, Birmingham. 2001-2003."
        }
    ],
    "Geographies": [
        {
            "GeoHierarchy": "The Thesaurus of Geographic Names\\World\\continents\\Asia\\nations\\",
            "GeoType": "Place of Origin",
            "GeographyID": 1496397,
            "GeographyTerm": "Nepal",
            "Latitude": "28 00",
            "LatitudeDirection": "N",
            "LatitudeNumber": 28.0,
            "Longitude": "084 00",
            "LongitudeDirection": "E",
            "LongitudeNumber": 84.0
        }
    ],
    "Images": [
        {
            "ID": 66446,
            "ImageURLs": {
                "Large": "http://static.thewalters.org/images/PS1_54.3012_Fnt_DD_T14.jpg?width=250",
                "Medium": "http://static.thewalters.org/images/PS1_54.3012_Fnt_DD_T14.jpg?width=150",
                "Raw": "http://static.thewalters.org/images/PS1_54.3012_Fnt_DD_T14.jpg",
                "Small": "http://static.thewalters.org/images/PS1_54.3012_Fnt_DD_T14.jpg?width=100",
                "Tiny": "http://static.thewalters.org/images/PS1_54.3012_Fnt_DD_T14.jpg?width=50"
            },
            "IsPrimary": true,
            "Rank": 1
        },
        {
            "ID": 66444,
            "ImageURLs": {
                "Large": "http://static.thewalters.org/images/PS1_54.3012_3Qtr_DD_T14.jpg?width=250",
                "Medium": "http://static.thewalters.org/images/PS1_54.3012_3Qtr_DD_T14.jpg?width=150",
                "Raw": "http://static.thewalters.org/images/PS1_54.3012_3Qtr_DD_T14.jpg",
                "Small": "http://static.thewalters.org/images/PS1_54.3012_3Qtr_DD_T14.jpg?width=100",
                "Tiny": "http://static.thewalters.org/images/PS1_54.3012_3Qtr_DD_T14.jpg?width=50"
            },
            "IsPrimary": false,
            "Rank": 2
        },
        {
            "ID": 66445,
            "ImageURLs": {
                "Large": "http://static.thewalters.org/images/PS1_54.3012_Back_DD_T14.jpg?width=250",
                "Medium": "http://static.thewalters.org/images/PS1_54.3012_Back_DD_T14.jpg?width=150",
                "Raw": "http://static.thewalters.org/images/PS1_54.3012_Back_DD_T14.jpg",
                "Small": "http://static.thewalters.org/images/PS1_54.3012_Back_DD_T14.jpg?width=100",
                "Tiny": "http://static.thewalters.org/images/PS1_54.3012_Back_DD_T14.jpg?width=50"
            },
            "IsPrimary": false,
            "Rank": 3
        },
        {
            "ID": 854,
            "ImageURLs": {
                "Large": "http://static.thewalters.org/images/ARG_54.3012_Fnt_UK.jpg?width=250",
                "Medium": "http://static.thewalters.org/images/ARG_54.3012_Fnt_UK.jpg?width=150",
                "Raw": "http://static.thewalters.org/images/ARG_54.3012_Fnt_UK.jpg",
                "Small": "http://static.thewalters.org/images/ARG_54.3012_Fnt_UK.jpg?width=100",
                "Tiny": "http://static.thewalters.org/images/ARG_54.3012_Fnt_UK.jpg?width=50"
            },
            "IsPrimary": false,
            "Rank": 200
        }
    ],
    "Inscriptions": "Unreadable",
    "Keywords": null,
    "Medium": "gilded copper alloy with traces of paint, turquoise",
    "MuseumLocation": {
        "DisplayCurrentLocation": "Link to Hackerman House: Cupola",
        "LocationID": 5009,
        "LocationString": null
    },
    "ObjectID": 17840,
    "ObjectName": "sculptures",
    "ObjectNumber": "54.3012",
    "OnView": 1,
    "Period": null,
    "Provenance": "John and Berthe Ford, Baltimore [date and mode of acquisition unknown]; Walters Art Museum, 2002, by gift.",
    "PublicAccessDate": "2008-09-25T17:09:35.887",
    "Reign": null,
    "RelatedObjects": null,
    "ResourceURL": "http://art.thewalters.org/detail/17840",
    "SortNumber": "    54  3012                                            ",
    "Style": "Khasamalla School",
    "Title": "Tara"
}