{
    "Classification": "Precious Stones & Gems",
    "Collection": null,
    "Creators": [
        {
            "ConcatDisplayName": "Near Eastern",
            "CreatorID": 16254,
            "Gender": null,
            "Role": "Artist"
        }
    ],
    "CreditLine": "Museum purchase, 1941",
    "Culture": null,
    "DateBeginYear": 0,
    "DateEndYear": 0,
    "DateText": "n.d.",
    "Description": "The scene on this seal depicts two addorsed, standing figures in long tufted robes, with hands raised in a posture of supplication. The scene also includes three registers of cuneiform inscription.",
    "Dimensions": "7/8 x 5/16 in. (2.3 x 0.8 cm) (h. x diam.)",
    "Dynasty": null,
    "Exhibitions": null,
    "Geographies": null,
    "Images": [
        {
            "ID": 8101,
            "ImageURLs": {
                "Large": "http://static.thewalters.org/images/PS1_42.611_SideA_DD_T06.jpg?width=250",
                "Medium": "http://static.thewalters.org/images/PS1_42.611_SideA_DD_T06.jpg?width=150",
                "Raw": "http://static.thewalters.org/images/PS1_42.611_SideA_DD_T06.jpg",
                "Small": "http://static.thewalters.org/images/PS1_42.611_SideA_DD_T06.jpg?width=100",
                "Tiny": "http://static.thewalters.org/images/PS1_42.611_SideA_DD_T06.jpg?width=50"
            },
            "IsPrimary": true,
            "Rank": 1
        },
        {
            "ID": 8102,
            "ImageURLs": {
                "Large": "http://static.thewalters.org/images/PS1_42.611_SideB_DD_T06.jpg?width=250",
                "Medium": "http://static.thewalters.org/images/PS1_42.611_SideB_DD_T06.jpg?width=150",
                "Raw": "http://static.thewalters.org/images/PS1_42.611_SideB_DD_T06.jpg",
                "Small": "http://static.thewalters.org/images/PS1_42.611_SideB_DD_T06.jpg?width=100",
                "Tiny": "http://static.thewalters.org/images/PS1_42.611_SideB_DD_T06.jpg?width=50"
            },
            "IsPrimary": false,
            "Rank": 2
        },
        {
            "ID": 8103,
            "ImageURLs": {
                "Large": "http://static.thewalters.org/images/PS1_42.611_SideC_DD_T06.jpg?width=250",
                "Medium": "http://static.thewalters.org/images/PS1_42.611_SideC_DD_T06.jpg?width=150",
                "Raw": "http://static.thewalters.org/images/PS1_42.611_SideC_DD_T06.jpg",
                "Small": "http://static.thewalters.org/images/PS1_42.611_SideC_DD_T06.jpg?width=100",
                "Tiny": "http://static.thewalters.org/images/PS1_42.611_SideC_DD_T06.jpg?width=50"
            },
            "IsPrimary": false,
            "Rank": 3
        },
        {
            "ID": 8104,
            "ImageURLs": {
                "Large": "http://static.thewalters.org/images/PS1_42.611_SideD_DD_T06.jpg?width=250",
                "Medium": "http://static.thewalters.org/images/PS1_42.611_SideD_DD_T06.jpg?width=150",
                "Raw": "http://static.thewalters.org/images/PS1_42.611_SideD_DD_T06.jpg",
                "Small": "http://static.thewalters.org/images/PS1_42.611_SideD_DD_T06.jpg?width=100",
                "Tiny": "http://static.thewalters.org/images/PS1_42.611_SideD_DD_T06.jpg?width=50"
            },
            "IsPrimary": false,
            "Rank": 4
        },
        {
            "ID": 8105,
            "ImageURLs": {
                "Large": "http://static.thewalters.org/images/PS1_42.611_Top_DD_T06.jpg?width=250",
                "Medium": "http://static.thewalters.org/images/PS1_42.611_Top_DD_T06.jpg?width=150",
                "Raw": "http://static.thewalters.org/images/PS1_42.611_Top_DD_T06.jpg",
                "Small": "http://static.thewalters.org/images/PS1_42.611_Top_DD_T06.jpg?width=100",
                "Tiny": "http://static.thewalters.org/images/PS1_42.611_Top_DD_T06.jpg?width=50"
            },
            "IsPrimary": false,
            "Rank": 5
        },
        {
            "ID": 32518,
            "ImageURLs": {
                "Large": "http://static.thewalters.org/images/CUR_42.611_VwA_UK.jpg?width=250",
                "Medium": "http://static.thewalters.org/images/CUR_42.611_VwA_UK.jpg?width=150",
                "Raw": "http://static.thewalters.org/images/CUR_42.611_VwA_UK.jpg",
                "Small": "http://static.thewalters.org/images/CUR_42.611_VwA_UK.jpg?width=100",
                "Tiny": "http://static.thewalters.org/images/CUR_42.611_VwA_UK.jpg?width=50"
            },
            "IsPrimary": false,
            "Rank": 6
        }
    ],
    "Inscriptions": "[Inscription]",
    "Keywords": null,
    "Medium": "hematite",
    "MuseumLocation": {
        "DisplayCurrentLocation": "Not On View",
        "LocationID": 1376,
        "LocationString": null
    },
    "ObjectID": 1220,
    "ObjectName": "cylinder seals",
    "ObjectNumber": "42.611",
    "OnView": 0,
    "Period": "Babylon I",
    "Provenance": "Sadie Jones (Mrs. Henry Walters), New York [date and mode of acquisition unknown]; Sale, Joseph Brummer, New York, 1941; Walters Art Museum, 1941, by purchase.",
    "PublicAccessDate": "2009-04-20T10:59:13.503",
    "Reign": null,
    "RelatedObjects": null,
    "ResourceURL": "http://art.thewalters.org/detail/1220",
    "SortNumber": "    42   611                                            ",
    "Style": null,
    "Title": "Cylinder Seal with Standing Figures and Inscription"
}